Workbook

Sheet Parámetros
A1: MILPÍN — Modelo de Adopción con Churn
A2: Proyección 48 meses · Valle del Yaqui DR-041 · Módulo 3
A3: PARÁMETROS DE ENTRADA — celdas en azul son modificables
A4: Parámetro | B4: Valor | C4: Notas
A5: Techo de mercado (ha) | B5: 5000 | C5: Ha máximas disponibles en el mercado objetivo
A6: Tasa de adquisición mensual | B6: 0.03 | C6: % del mercado disponible que entra cada mes
A7: Churn mensual | B7: 0.05 | C7: % de ha activas que abandonan cada mes
A8: Precio Plan 1 (MXN/ha/mes) | B8: 20 | C8: Plan 1: $240/ha/año ÷ 12 = $20/ha/mes
A9: Infra stack actual (MXN/año) | B9: 19360 | C9: Stack actual = ~$1,613/mes
A10: Infra Azure (MXN/año) | B10: 292680 | C10: Azure estimado = ~$24,390/mes
A11: Stack seleccionado | B11: actual | C11: Escribir exactamente: 'actual' o 'azure'
A12: PARÁMETROS DERIVADOS — calculados automáticamente
A13: Parámetro | B13: Valor | C13: Notas
A14: Costo mensual infra (MXN/mes) | B14: =IF(LOWER(B11)="azure",B10/12,B9/12) -> 1613.3333 | C14: Cambia automáticamente según stack seleccionado
A15: Acq. rate pesimista (× 0.6) | B15: =B6*0.6 -> 0.018 | C15: Escenario pesimista: adquisición 40% más lenta
A16: Churn pesimista (× 2) | B16: =B7*2 -> 0.1 | C16: Escenario pesimista: el doble de abandono
A17: Acq. rate optimista (× 1.5) | B17: =B6*1.5 -> 0.045 | C17: Escenario optimista: 50% más rápida
A18: Churn optimista (÷ 2) | B18: =B7*0.5 -> 0.025 | C18: Escenario optimista: la mitad de abandono
A19: KPIs — EQUILIBRIO DEL SISTEMA (escenario base)
A20: Parámetro | B20: Valor | C20: Notas
A21: Ha en equilibrio real (base) | B21: =B5*B6/(B6+B7) -> 1875 | C21: Techo × acq ÷ (acq + churn) → límite real del sistema
A22: % del techo alcanzable | B22: =B21/B5 -> 0.375 | C22: Ha equilibrio ÷ techo de mercado
A23: Ingreso mensual estable (MXN) | B23: =B21*B8 -> 37500 | C23: Equilibrio × precio/ha/mes
A24: ¿Plan 1 cubre costos en equilibrio? | B24: =IF(B23>=B14,"✓ Sí — modelo viable","✗ No — revisar churn o precio") -> ✓ Sí — modelo viable | C24: Compara ingreso estable vs costo fijo mensual
A25: LTV estimado (MXN/ha) | B25: =IF(B7>0,B8/B7,0) -> 400 | C25: Precio/mes ÷ churn = valor de vida media por hectárea
A26: Vida media de ha activa (meses) | B26: =IF(B7>0,1/B7,0) -> 20 | C26: 1 ÷ churn mensual
A28: CONVENCIÓN DE COLORES (estándar financiero)
A29: Azul / fondo amarillo | B29: Azul / Amarillo | C29: Input — valor que el usuario puede modificar
A30: Negro sin fondo | B30: Negro | C30: Fórmula — calculado automáticamente
A31: Hoja Proyección 48M | C31: Simulación mes a mes + gráfica dinámica

Sheet Proyección 48M
A1: MILPÍN — Proyección 48 Meses · Ingresos por Escenario vs Costo Fijo
A2: Mes | B2: Ha Base | C2: Ha Pesimista | D2: Ha Optimista | E2: Rev Base (MXN/mes) | F2: Rev Pesimista (MXN/mes) | G2: Rev Optimista (MXN/mes) | H2: Costo Fijo (MXN/mes)
A3: Fórmulas referencian hoja 'Parámetros' · Modifica los valores allí y esta tabla se actualiza automáticamente
A4: M1 | B4: =Parámetros!$B$6*Parámetros!$B$5 -> 150 | C4: =Parámetros!$B$15*Parámetros!$B$5 -> 90 | D4: =Parámetros!$B$17*Parámetros!$B$5 -> 225 | E4: =B4*Parámetros!$B$8 -> 3000 | F4: =C4*Parámetros!$B$8 -> 1800 | G4: =D4*Parámetros!$B$8 -> 4500 | H4: =Parámetros!$B$14 -> 1613.3333
A5: M2 | B5: =B4*(1-Parámetros!$B$6-Parámetros!$B$7)+Parámetros!$B$6*Parámetros!$B$5 -> 288 | C5: =C4*(1-Parámetros!$B$15-Parámetros!$B$16)+Parámetros!$B$15*Parámetros!$B$5 -> 169.38 | D5: =D4*(1-Parámetros!$B$17-Parámetros!$B$18)+Parámetros!$B$17*Parámetros!$B$5 -> 434.25 | E5: =B5*Parámetros!$B$8 -> 5760 | F5: =C5*Parámetros!$B$8 -> 3387.6 | G5: =D5*Parámetros!$B$8 -> 8685 | H5: =Parámetros!$B$14 -> 1613.3333
A6: M3 | B6: =B5*(1-Parámetros!$B$6-Parámetros!$B$7)+Parámetros!$B$6*Parámetros!$B$5 -> 414.96 | C6: =C5*(1-Parámetros!$B$15-Parámetros!$B$16)+Parámetros!$B$15*Parámetros!$B$5 -> 239.39316 | D6: =D5*(1-Parámetros!$B$17-Parámetros!$B$18)+Parámetros!$B$17*Parámetros!$B$5 -> 628.8525 | E6: =B6*Parámetros!$B$8 -> 8299.2 | F6: =C6*Parámetros!$B$8 -> 4787.8632 | G6: =D6*Parámetros!$B$8 -> 12577.05 | H6: =Parámetros!$B$14 -> 1613.3333
A7: M4 | B7: =B6*(1-Parámetros!$B$6-Parámetros!$B$7)+Parámetros!$B$6*Parámetros!$B$5 -> 531.7632 | C7: =C6*(1-Parámetros!$B$15-Parámetros!$B$16)+Parámetros!$B$15*Parámetros!$B$5 -> 301.14477 | D7: =D6*(1-Parámetros!$B$17-Parámetros!$B$18)+Parámetros!$B$17*Parámetros!$B$5 -> 809.83282 | E7: =B7*Parámetros!$B$8 -> 10635.264 | F7: =C7*Parámetros!$B$8 -> 6022.8953 | G7: =D7*Parámetros!$B$8 -> 16196.656 | H7: =Parámetros!$B$14 -> 1613.3333
A8: M5 | B8: =B7*(1-Parámetros!$B$6-Parámetros!$B$7)+Parámetros!$B$6*Parámetros!$B$5 -> 639.22214 | C8: =C7*(1-Parámetros!$B$15-Parámetros!$B$16)+Parámetros!$B$15*Parámetros!$B$5 -> 355.60968 | D8: =D7*(1-Parámetros!$B$17-Parámetros!$B$18)+Parámetros!$B$17*Parámetros!$B$5 -> 978.14453 | E8: =B8*Parámetros!$B$8 -> 12784.443 | F8: =C8*Parámetros!$B$8 -> 7112.1937 | G8: =D8*Parámetros!$B$8 -> 19562.891 | H8: =Parámetros!$B$14 -> 1613.3333
A9: M6 | B9: =B8*(1-Parámetros!$B$6-Parámetros!$B$7)+Parámetros!$B$6*Parámetros!$B$5 -> 738.08437 | C9: =C8*(1-Parámetros!$B$15-Parámetros!$B$16)+Parámetros!$B$15*Parámetros!$B$5 -> 403.64774 | D9: =D8*(1-Parámetros!$B$17-Parámetros!$B$18)+Parámetros!$B$17*Parámetros!$B$5 -> 1134.6744 | E9: =B9*Parámetros!$B$8 -> 14761.687 | F9: =C9*Parámetros!$B$8 -> 8072.9548 | G9: =D9*Parámetros!$B$8 -> 22693.488 | H9: =Parámetros!$B$14 -> 1613.3333
A10: M7 | B10: =B9*(1-Parámetros!$B$6-Parámetros!$B$7)+Parámetros!$B$6*Parámetros!$B$5 -> 829.03762 | C10: =C9*(1-Parámetros!$B$15-Parámetros!$B$16)+Parámetros!$B$15*Parámetros!$B$5 -> 446.01731 | D10: =D9*(1-Parámetros!$B$17-Parámetros!$B$18)+Parámetros!$B$17*Parámetros!$B$5 -> 1280.2472 | E10: =B10*Parámetros!$B$8 -> 16580.752 | F10: =C10*Parámetros!$B$8 -> 8920.3462 | G10: =D10*Parámetros!$B$8 -> 25604.944 | H10: =Parámetros!$B$14 -> 1613.3333
A11: M8 | B11: =B10*(1-Parámetros!$B$6-Parámetros!$B$7)+Parámetros!$B$6*Parámetros!$B$5 -> 912.71461 | C11: =C10*(1-Parámetros!$B$15-Parámetros!$B$16)+Parámetros!$B$15*Parámetros!$B$5 -> 483.38727 | D11: =D10*(1-Parámetros!$B$17-Parámetros!$B$18)+Parámetros!$B$17*Parámetros!$B$5 -> 1415.6299 | E11: =B11*Parámetros!$B$8 -> 18254.292 | F11: =C11*Parámetros!$B$8 -> 9667.7453 | G11: =D11*Parámetros!$B$8 -> 28312.598 | H11: =Parámetros!$B$14 -> 1613.3333
A12: M9 | B12: =B11*(1-Parámetros!$B$6-Parámetros!$B$7)+Parámetros!$B$6*Parámetros!$B$5 -> 989.69744 | C12: =C11*(1-Parámetros!$B$15-Parámetros!$B$16)+Parámetros!$B$15*Parámetros!$B$5 -> 516.34757 | D12: =D11*(1-Parámetros!$B$17-Parámetros!$B$18)+Parámetros!$B$17*Parámetros!$B$5 -> 1541.5358 | E12: =B12*Parámetros!$B$8 -> 19793.949 | F12: =C12*Parámetros!$B$8 -> 10326.951 | G12: =D12*Parámetros!$B$8 -> 30830.716 | H12: =Parámetros!$B$14 -> 1613.3333
A13: M10 | B13: =B12*(1-Parámetros!$B$6-Parámetros!$B$7)+Parámetros!$B$6*Parámetros!$B$5 -> 1060.5216 | C13: =C12*(1-Parámetros!$B$15-Parámetros!$B$16)+Parámetros!$B$15*Parámetros!$B$5 -> 545.41856 | D13: =D12*(1-Parámetros!$B$17-Parámetros!$B$18)+Parámetros!$B$17*Parámetros!$B$5 -> 1658.6283 | E13: =B13*Parámetros!$B$8 -> 21210.433 | F13: =C13*Parámetros!$B$8 -> 10908.371 | G13: =D13*Parámetros!$B$8 -> 33172.566 | H13: =Parámetros!$B$14 -> 1613.3333
A14: M11 | B14: =B13*(1-Parámetros!$B$6-Parámetros!$B$7)+Parámetros!$B$6*Parámetros!$B$5 -> 1125.6799 | C14: =C13*(1-Parámetros!$B$15-Parámetros!$B$16)+Parámetros!$B$15*Parámetros!$B$5 -> 571.05917 | D14: =D13*(1-Parámetros!$B$17-Parámetros!$B$18)+Parámetros!$B$17*Parámetros!$B$5 -> 1767.5243 | E14: =B14*Parámetros!$B$8 -> 22513.598 | F14: =C14*Parámetros!$B$8 -> 11421.183 | G14: =D14*Parámetros!$B$8 -> 35350.486 | H14: =Parámetros!$B$14 -> 1613.3333
A15: M12 | B15: =B14*(1-Parámetros!$B$6-Parámetros!$B$7)+Parámetros!$B$6*Parámetros!$B$5 -> 1185.6255 | C15: =C14*(1-Parámetros!$B$15-Parámetros!$B$16)+Parámetros!$B$15*Parámetros!$B$5 -> 593.67418 | D15: =D14*(1-Parámetros!$B$17-Parámetros!$B$18)+Parámetros!$B$17*Parámetros!$B$5 -> 1868.7976 | E15: =B15*Parámetros!$B$8 -> 23712.51 | F15: =C15*Parámetros!$B$8 -> 11873.484 | G15: =D15*Parámetros!$B$8 -> 37375.952 | H15: =Parámetros!$B$14 -> 1613.3333
A16: M13 | B16: =B15*(1-Parámetros!$B$6-Parámetros!$B$7)+Parámetros!$B$6*Parámetros!$B$5 -> 1240.7755 | C16: =C15*(1-Parámetros!$B$15-Parámetros!$B$16)+Parámetros!$B$15*Parámetros!$B$5 -> 613.62063 | D16: =D15*(1-Parámetros!$B$17-Parámetros!$B$18)+Parámetros!$B$17*Parámetros!$B$5 -> 1962.9818 | E16: =B16*Parámetros!$B$8 -> 24815.51 | F16: =C16*Parámetros!$B$8 -> 12272.413 | G16: =D16*Parámetros!$B$8 -> 39259.636 | H16: =Parámetros!$B$14 -> 1613.3333
... A51: M48 | B51: =B50*(1-Parámetros!$B$6-Parámetros!$B$7)+Parámetros!$B$6*Parámetros!$B$5 -> 1840.7377 | C51: =C50*(1-Parámetros!$B$15-Parámetros!$B$16)+Parámetros!$B$15*Parámetros!$B$5 -> 760.87172 | D51: =D50*(1-Parámetros!$B$17-Parámetros!$B$18)+Parámetros!$B$17*Parámetros!$B$5 -> 3115.5973 | E51: =B51*Parámetros!$B$8 -> 36814.753 | F51: =C51*Parámetros!$B$8 -> 15217.434 | G51: =D51*Parámetros!$B$8 -> 62311.947 | H51: =Parámetros!$B$14 -> 1613.3333
